froeling/__init__.py
froeling/__main__.py
froeling/metrics.py
froeling/token.py
froeling_metrics-1.0.0.dist-info/METADATA
froeling_metrics-1.0.0.dist-info/WHEEL
froeling_metrics-1.0.0.dist-info/top_level.txt
froeling_metrics-1.0.0.dist-info/RECORD
