Metadata-Version: 2.1
Name: froeling-metrics
Version: 1.0.0
Summary: Python module for scraping facility metrics from the Fröling Connect web portal
Classifier: Programming Language :: Python :: 3
Requires-Python: >=3.7
Requires-Dist: requests
